GreenPonik_Atlas_Scientific_OEM_i2c/AtlasOEMI2c.py
GreenPonik_Atlas_Scientific_OEM_i2c/CommonsI2c.py
GreenPonik_Atlas_Scientific_OEM_i2c/ECI2c.py
GreenPonik_Atlas_Scientific_OEM_i2c/PHI2c.py
GreenPonik_Atlas_Scientific_OEM_i2c/__init__.py
tests/__init__.py
tests/test_ECI2c.py
tests/test_PHI2c.py
greenponik_atlas_scientific_oem_i2c-0.0.8.dist-info/METADATA
greenponik_atlas_scientific_oem_i2c-0.0.8.dist-info/WHEEL
greenponik_atlas_scientific_oem_i2c-0.0.8.dist-info/top_level.txt
greenponik_atlas_scientific_oem_i2c-0.0.8.dist-info/RECORD
