Metadata-Version: 2.1
Name: greenponik-atlas-scientific-oem-i2c
Version: 0.0.8
Summary: GreenPonik library to use Atlas Scientific OEM EC and pH circuits on SMBus/I2C
Home-page: https://github.com/GreenPonik/GreenPonik_Atlas_Scientific_OEM_i2c
Author: GreenPonik SAS
Author-email: contact@greenponik.com
License: MIT
Project-URL: Source, https://github.com/GreenPonik/        GreenPonik_Atlas_Scientific_i2c/
Project-URL: Bug Reports, https://github.com/GreenPonik/        GreenPonik_Atlas_Scientific_i2c/issues
Keywords: GreenPonik hydroponics SMBus/i2c EC Electro Conductivity and pH          reader Atlas Scientific OEM python hardware diy iot raspberry pi
Platform: UNKNOWN
Classifier: Programming Language :: Python :: 3
Classifier: License :: OSI Approved :: MIT License
Classifier: Operating System :: OS Independent
Requires-Python: >=3.6.0
